README.md
setup.cfg
setup.py
sanic_macrobase/__init__.py
sanic_macrobase/config.py
sanic_macrobase/driver.py
sanic_macrobase/endpoint.py
sanic_macrobase/exceptions.py
sanic_macrobase/helpers.py
sanic_macrobase/hook.py
sanic_macrobase/route.py
sanic_macrobase.egg-info/PKG-INFO
sanic_macrobase.egg-info/SOURCES.txt
sanic_macrobase.egg-info/dependency_links.txt
sanic_macrobase.egg-info/requires.txt
sanic_macrobase.egg-info/top_level.txt