Metadata-Version: 1.0
Name: sanic-macrobase
Version: 0.0.8
Summary: Sanic driver for macrobase framework
Home-page: https://github.com/mbcores/sanic-macrobase
Author: Alexey Shagaleev
Author-email: alexey.shagaleev@yandex.ru
License: MIT
Platform: UNKNOWN
